misaki/__init__.py
misaki/cutlet.py
misaki/data/__init__.py
misaki/data/gb_gold.json
misaki/data/gb_silver.json
misaki/data/ja_words.txt
misaki/data/us_gold.json
misaki/data/us_silver.json
misaki/data/vi_acronyms.json
misaki/data/vi_symbols.json
misaki/data/vi_teencode.json
misaki/en.py
misaki/espeak.py
misaki/g2pkc/README.md
misaki/g2pkc/__init__.py
misaki/g2pkc/english.py
misaki/g2pkc/g2pk.py
misaki/g2pkc/idioms.txt
misaki/g2pkc/numerals.py
misaki/g2pkc/regular.py
misaki/g2pkc/rules.txt
misaki/g2pkc/special.py
misaki/g2pkc/table.csv
misaki/g2pkc/utils.py
misaki/he.py
misaki/ja.py
misaki/ko.py
misaki/num2kana.py
misaki/py.typed
misaki/token.py
misaki/tone_sandhi.py
misaki/transcription.py
misaki/vi.py
misaki/vi_cleaner/README.md
misaki/vi_cleaner/__init__.py
misaki/vi_cleaner/abbreviation_vi.py
misaki/vi_cleaner/acronym_vi.py
misaki/vi_cleaner/cleaner.py
misaki/vi_cleaner/currency_vi.py
misaki/vi_cleaner/datestime_vi.py
misaki/vi_cleaner/letter_vi.py
misaki/vi_cleaner/measurement_vi.py
misaki/vi_cleaner/num2vi.py
misaki/vi_cleaner/numberical_vi.py
misaki/vi_cleaner/passage_utils.py
misaki/vi_cleaner/roman_number_vi.py
misaki/vi_cleaner/sentence_utils.py
misaki/vi_cleaner/symbol_vi.py
misaki/zh.py
misaki/zh_frontend.py
misaki/zh_normalization/README.md
misaki/zh_normalization/__init__.py
misaki/zh_normalization/char_convert.py
misaki/zh_normalization/chronology.py
misaki/zh_normalization/constants.py
misaki/zh_normalization/num.py
misaki/zh_normalization/phonecode.py
misaki/zh_normalization/quantifier.py
misaki/zh_normalization/text_normalization.py
misaki_fork-0.9.6.dist-info/WHEEL
misaki_fork-0.9.6.dist-info/METADATA
misaki_fork-0.9.6.dist-info/RECORD
