Metadata-Version: 2.3
Name: misaki-fork
Version: 0.9.6
Summary: G2P engine for TTS
Author: hexgrad
Author-email: hexgrad <hello@hexgrad.com>
License:                                  Apache License
Classifier: Programming Language :: Python :: 3
Classifier: License :: OSI Approved :: Apache Software License
Classifier: Operating System :: OS Independent
Requires-Dist: addict>=2.4.0
Requires-Dist: pip>=25.0.1
Requires-Dist: regex>=2024.11.6
Requires-Dist: espeakng-loader>=0.2.4 ; extra == 'en'
Requires-Dist: num2words>=0.5.14 ; extra == 'en'
Requires-Dist: phonemizer-fork>=3.3.2 ; extra == 'en'
Requires-Dist: spacy>=3.7.5 ; extra == 'en'
Requires-Dist: spacy-curated-transformers>=0.2.2 ; extra == 'en'
Requires-Dist: torch>=2.5.1 ; extra == 'en'
Requires-Dist: transformers>=4.46.3 ; extra == 'en'
Requires-Dist: fugashi>=1.4.0 ; extra == 'ja'
Requires-Dist: jaconv>=0.4.0 ; extra == 'ja'
Requires-Dist: mojimoji>=0.0.13 ; extra == 'ja'
Requires-Dist: pyopenjtalk>=0.4.1 ; extra == 'ja'
Requires-Dist: unidic>=1.1.0 ; extra == 'ja'
Requires-Dist: jamo>=0.4.1 ; extra == 'ko'
Requires-Dist: mecab-python3>=1.0.12 ; extra == 'ko'
Requires-Dist: nltk>=3.9.1 ; extra == 'ko'
Requires-Dist: unidic-lite>=1.0.8 ; extra == 'ko'
Requires-Dist: num2words>=0.5.14 ; extra == 'vi'
Requires-Dist: spacy>=3.7.5 ; extra == 'vi'
Requires-Dist: spacy-curated-transformers>=0.2.2 ; extra == 'vi'
Requires-Dist: underthesea>=6.8.4 ; extra == 'vi'
Requires-Dist: vietnam-number>=1.0.3 ; extra == 'vi'
Requires-Dist: cn2an>=0.5.23 ; extra == 'zh'
Requires-Dist: jieba>=0.42.1 ; extra == 'zh'
Requires-Dist: ordered-set>=4.1.0 ; extra == 'zh'
Requires-Dist: pypinyin>=0.55.0 ; extra == 'zh'
Requires-Dist: pypinyin-dict>=0.9.0 ; extra == 'zh'
Requires-Python: >=3.8, <3.13
Provides-Extra: en
Provides-Extra: ja
Provides-Extra: ko
Provides-Extra: vi
Provides-Extra: zh
